shellio/__init__.py
shellio/shellio.py
shellio-1.0.1.dist-info/licenses/LICENSE
shellio-1.0.1.dist-info/METADATA
shellio-1.0.1.dist-info/WHEEL
shellio-1.0.1.dist-info/top_level.txt
shellio-1.0.1.dist-info/RECORD
