Metadata-Version: 2.4
Name: shellio
Version: 1.0.1
Summary: ShellIO is a Python interface for interacting with Unix-like shells
Home-page: https://github.com/mateuszzebala/shellio
Author: Mateusz Zębala
Author-email: mateusz.zebala.pl@gmail.com
License: MIT
Classifier: Programming Language :: Python :: 3
Classifier: Programming Language :: Python :: 3.9
Classifier: Programming Language :: Python :: 3.10
Classifier: Programming Language :: Python :: 3.11
Classifier: License :: OSI Approved :: MIT License
Classifier: Operating System :: OS Independent
Classifier: Environment :: Console
Classifier: Topic :: Terminals
Classifier: Topic :: Software Development :: Libraries
Classifier: Intended Audience :: Developers
License-File: LICENSE
Dynamic: author
Dynamic: author-email
Dynamic: classifier
Dynamic: description
Dynamic: description-content-type
Dynamic: home-page
Dynamic: license
Dynamic: license-file
Dynamic: summary
